[{"card_name": "Alchemist Prodigy", "number": 6, "shape": "normal"}, {"card_name": "Gawr Gura", "number": 30, "shape": "normal"}, {"card_name": "Azax-Azog, the Demon Thane", "number": 56, "shape": "normal"}, {"card_name": "Battle of the Bands", "number": 88, "shape": "battle split"}, {"card_name": "Ninomae Ina'nis", "number": 128, "shape": "normal"}, {"card_name": "Amelia Watson", "number": 7, "shape": "normal"}, {"card_name": "Geralf, the Stitcher", "number": 31, "shape": "normal"}, {"card_name": "Calliope Mori", "number": 59, "shape": "normal"}, {"card_name": "The Great Conquereors from the East", "number": 100, "shape": "class"}, {"card_name": "Symbiotic Hydroid", "number": 131, "shape": "normal"}, {"card_name": "Arsteel, Weenie Commander", "number": 9, "shape": "normal"}, {"card_name": "Lo and Behold", "number": 33, "shape": "normal"}, {"card_name": "Hydra", "number": 67, "shape": "normal"}, {"card_name": "Takanashi Kiara", "number": 111, "shape": "normal"}, {"card_name": "Virtue of Creation", "number": 135, "shape": "adventure"}, {"card_name": "Bant Foresummoner", "number": 10, "shape": "normal"}, {"card_name": "Time Walkman", "number": 45, "shape": "normal"}, {"card_name": "Locthwain Ascendancy", "number": 69, "shape": "normal"}, {"card_name": "Temujin, Mongol Unifier", "number": 114, "shape": "transform double faced"}, {"card_name": "Always-Useful Fungus", "number": 117, "shape": "normal"}, {"card_name": "Colonel Mustard", "number": 15, "shape": "normal"}, {"card_name": "Advisor Class", "number": 23, "shape": "class"}, {"card_name": "Mana Erosion", "number": 71, "shape": "normal"}, {"card_name": "Ambush Trap", "number": 84, "shape": "normal"}, {"card_name": "Chasmfiend", "number": 120, "shape": "normal"}, {"card_name": "Courageous Knight", "number": 16, "shape": "adventure"}, {"card_name": "Alchemist", "number": 24, "shape": "class"}, {"card_name": "Necromancer's Tome", "number": 72, "shape": "normal"}, {"card_name": "Attila, the Scourge of God", "number": 85, "shape": "normal"}, {"card_name": "Courage", "number": 121, "shape": "normal"}, {"card_name": "Teferi's Trap", "number": 20, "shape": "normal"}, {"card_name": "Double-Dip", "number": 26, "shape": "normal"}, {"card_name": "All for Nothing", "number": 52, "shape": "normal"}, {"card_name": "Blood Moon", "number": 90, "shape": "normal"}, {"card_name": "Gatesage Elf", "number": 123, "shape": "normal"}, {"card_name": "Wrapcaster Mage", "number": 22, "shape": "normal"}, {"card_name": "Epiphany", "number": 28, "shape": "normal"}, {"card_name": "Assassin Class", "number": 54, "shape": "class"}, {"card_name": "Goblin Cavaclade", "number": 97, "shape": "normal"}, {"card_name": "Great Grey Wolf Sif", "number": 124, "shape": "normal"}, {"card_name": "Battlefield Scavenging", "number": 11, "shape": "normal"}, {"card_name": "Leitmotif", "number": 32, "shape": "normal"}, {"card_name": "Dead or Alive", "number": 61, "shape": "normal"}, {"card_name": "Merchant Class", "number": 103, "shape": "class"}, {"card_name": "Lumbering River-King", "number": 126, "shape": "normal"}, {"card_name": "Benevolent Blessing", "number": 12, "shape": "normal"}, {"card_name": "Most Perfect Idol", "number": 35, "shape": "normal"}, {"card_name": "Demon of Forgotten Desires", "number": 62, "shape": "normal"}, {"card_name": "Phyrexian Proclamation", "number": 104, "shape": "normal"}, {"card_name": "Might of the Ancestors", "number": 127, "shape": "normal"}, {"card_name": "Perfected Reality Excision", "number": 18, "shape": "normal"}, {"card_name": "Undo Reality", "number": 46, "shape": "normal"}, {"card_name": "Demonic Gift", "number": 63, "shape": "normal"}, {"card_name": "Power", "number": 105, "shape": "normal"}, {"card_name": "Predatory Might", "number": 129, "shape": "normal"}, {"card_name": "Resonant Sentries", "number": 19, "shape": "normal"}, {"card_name": "Wisdom", "number": 51, "shape": "normal"}, {"card_name": "Devastating Plague", "number": 64, "shape": "normal"}, {"card_name": "Punishment Stone", "number": 106, "shape": "normal"}, {"card_name": "Spawning Spider", "number": 130, "shape": "normal"}, {"card_name": "Thopter of Healing", "number": 21, "shape": "normal"}, {"card_name": "Dovin's Aether Whales", "number": 27, "shape": "normal"}, {"card_name": "Frenzy", "number": 65, "shape": "normal"}, {"card_name": "Pyreborn Phoenix", "number": 107, "shape": "normal"}, {"card_name": "Veline, Nature's Warden", "number": 134, "shape": "normal"}, {"card_name": "Aparchet's Familiar", "number": 8, "shape": "normal"}, {"card_name": "Metacognition", "number": 34, "shape": "normal"}, {"card_name": "Lich's Restoration", "number": 68, "shape": "normal"}, {"card_name": "Ragthrax, Lord of Flame", "number": 108, "shape": "normal"}, {"card_name": "Discordant Monstro", "number": 122, "shape": "normal"}, {"card_name": "Carcosan Guard", "number": 13, "shape": "normal"}, {"card_name": "Quell", "number": 38, "shape": "normal"}, {"card_name": "Malasekth III, The Expander", "number": 70, "shape": "normal"}, {"card_name": "Tamerlane, Timurid Emperor", "number": 112, "shape": "normal"}, {"card_name": "Guardian of Growth", "number": 125, "shape": "normal"}, {"card_name": "Chromatic Seal", "number": 14, "shape": "normal"}, {"card_name": "Untitled Sonata", "number": 48, "shape": "normal"}, {"card_name": "One with Nothingness", "number": 74, "shape": "normal"}, {"card_name": "BanBans Lesson", "number": 86, "shape": "normal"}, {"card_name": "Tools of Recovery", "number": 133, "shape": "normal"}, {"card_name": "Mentor of Errantry", "number": 17, "shape": "normal"}, {"card_name": "Volatile Ooze", "number": 49, "shape": "normal"}, {"card_name": "Putrefying Parasite", "number": 76, "shape": "normal"}, {"card_name": "Chimney Dragon", "number": 91, "shape": "normal"}, {"card_name": "Biomancer Class", "number": 118, "shape": "class"}, {"card_name": "e"}, {"card_name": "Charge Up", "number": 25, "shape": "normal"}, {"card_name": "Sesskit, The Frozen Embrace", "number": 79, "shape": "normal"}, {"card_name": "Electro-Static-Tricity", "number": 93, "shape": "normal"}, {"card_name": "Bitter Hermit", "number": 119, "shape": "transform double faced"}, {"card_name": "e"}, {"card_name": "Fall into Dreams", "number": 29, "shape": "normal"}, {"card_name": "Thing from the Swamp", "number": 82, "shape": "normal"}, {"card_name": "Forger of Flames", "number": 96, "shape": "normal"}, {"card_name": "Woodland Bears", "number": 136, "shape": "normal"}, {"card_name": "e"}, {"card_name": "Nimbus Eidolon", "number": 36, "shape": "normal"}, {"card_name": "Avenger of Ash", "number": 55, "shape": "normal"}, {"card_name": "The Golden Horde", "number": 99, "shape": "normal"}, {"card_name": "e"}, {"card_name": "e"}, {"card_name": "Pestersage", "number": 37, "shape": "normal"}, {"card_name": "Azax-Azog's Contract", "number": 57, "shape": "normal"}, {"card_name": "Keshik", "number": 101, "shape": "normal"}, {"card_name": "e"}, {"card_name": "e"}, {"card_name": "Restless Spook", "number": 39, "shape": "normal"}, {"card_name": "Reassembling Scaab", "number": 77, "shape": "normal"}, {"card_name": "Mangudai", "number": 102, "shape": "normal"}, {"card_name": "e"}, {"card_name": "e"}, {"card_name": "Sea Skipper", "number": 40, "shape": "normal"}, {"card_name": "Rot Swap", "number": 78, "shape": "normal"}, {"card_name": "Stoke the Blaze", "number": 109, "shape": "normal"}, {"card_name": "e"}, {"card_name": "e"}, {"card_name": "Sing", "number": 41, "shape": "normal"}, {"card_name": "Bugler Rat", "number": 58, "shape": "normal"}, {"card_name": "Tarkan", "number": 113, "shape": "normal"}, {"card_name": "e"}, {"card_name": "e"}, {"card_name": "Sorcerer's Umbrella", "number": 42, "shape": "transform double faced"}, {"card_name": "Compleated Sacrifice", "number": 60, "shape": "normal"}, {"card_name": "Wrath of the Dragons", "number": 116, "shape": "normal"}, {"card_name": "e"}, {"card_name": "e"}, {"card_name": "Submitted", "number": 43, "shape": "normal"}, {"card_name": "Hankon's Paladin", "number": 66, "shape": "normal"}, {"card_name": "Barroom Brawler", "number": 87, "shape": "normal"}, {"card_name": "e"}, {"card_name": "e"}, {"card_name": "Subtracti[ ]V[ ]e[ ]text[ ]", "number": 44, "shape": "normal"}, {"card_name": "Night Market Smuggler", "number": 73, "shape": "normal"}, {"card_name": "Beneath the Brain", "number": 89, "shape": "normal"}, {"card_name": "e"}, {"card_name": "e"}, {"card_name": "Unprompted Advance", "number": 47, "shape": "normal"}, {"card_name": "Poppet Witch", "number": 75, "shape": "normal"}, {"card_name": "Countdown", "number": 92, "shape": "transform double faced"}, {"card_name": "e"}, {"card_name": "e"}, {"card_name": "Waterdeep Archmage", "number": 50, "shape": "normal"}, {"card_name": "Spooky Storyteller", "number": 80, "shape": "normal"}, {"card_name": "Energy Blast", "number": 94, "shape": "normal"}, {"card_name": "e"}, {"card_name": "e"}, {"card_name": "e"}, {"card_name": "Stalker of Vast Reaches", "number": 81, "shape": "normal"}, {"card_name": "Feigned Retreat", "number": 95, "shape": "normal"}, {"card_name": "e"}, {"card_name": "e"}, {"card_name": "e"}, {"card_name": "Uncover the Truth", "number": 83, "shape": "normal"}, {"card_name": "Gold-Cursed Goblin", "number": 98, "shape": "normal"}, {"card_name": "e"}, {"card_name": "e"}, {"card_name": "e"}, {"card_name": "e"}, {"card_name": "Stone Rain", "number": 110, "shape": "normal"}, {"card_name": "e"}, {"card_name": "er"}, {"card_name": "er"}, {"card_name": "er"}, {"card_name": "er"}, "a->gold", {"card_name": "The Magic Flute", "number": 163, "shape": "normal"}, {"card_name": "Curse Broker", "number": 144, "shape": "normal"}, {"card_name": "Beast Blood Pellets", "number": 139, "shape": "normal"}, {"card_name": "Towards Beyond", "number": 194, "shape": "normal"}, {"card_name": "Gym Class", "number": 154, "shape": "normal"}, {"card_name": "Adventuring Sage", "number": 137, "shape": "normal"}, {"card_name": "Nevinyrral's Tome", "number": 168, "shape": "normal"}, {"card_name": "Goblin Storyteller", "number": 152, "shape": "normal"}, {"card_name": "Snagwood Shaman", "number": 188, "shape": "normal"}, {"card_name": "Sigardian Vanguard", "number": 185, "shape": "normal"}, {"card_name": "Lightbound Sprite", "number": 162, "shape": "normal"}, {"card_name": "Relive the Nightmares", "number": 177, "shape": "normal"}, {"card_name": "Specialized Strategist", "number": 189, "shape": "normal"}, {"card_name": "Wither-Blade Khenra", "number": 199, "shape": "normal"}, {"card_name": "e"}, {"card_name": "Return to Nyx", "number": 179, "shape": "normal"}, {"card_name": "Prowling Amygdala", "number": 174, "shape": "normal"}, {"card_name": "Rax, Sawtooth Boss", "number": 175, "shape": "normal"}, {"card_name": "e"}, {"card_name": "e"}, {"card_name": "Sweeping Denial", "number": 193, "shape": "normal"}, {"card_name": "Skyfall", "number": 186, "shape": "normal"}, {"card_name": "Remove All Traces", "number": 178, "shape": "normal"}, {"card_name": "e"}, {"card_name": "e"}, {"card_name": "e"}, {"card_name": "A Strange Dream", "number": 191, "shape": "saga"}, {"card_name": "e"}, {"card_name": "e"}, {"card_name": "e"}, {"card_name": "e"}, {"card_name": "Death Augur", "number": 147, "shape": "normal"}, {"card_name": "e"}, {"card_name": "e"}, {"card_name": "e"}, {"card_name": "e"}, {"card_name": "Strands of Shadow", "number": 190, "shape": "normal"}, {"card_name": "e"}, {"card_name": "e"}, {"card_name": "e"}, {"card_name": "er"}, {"card_name": "er"}, {"card_name": "er"}, {"card_name": "er"}, {"card_name": "er"}, {"card_name": "Sand Scour", "number": 181, "shape": "normal"}, {"card_name": "Marty McFly, Temporal Displacer", "number": 165, "shape": "normal"}, {"card_name": "Pharika, Blight-Blessed", "number": 172, "shape": "normal"}, {"card_name": "La Hire", "number": 160, "shape": "normal"}, {"card_name": "Skyrider Protector", "number": 187, "shape": "normal"}, {"card_name": "Late Night Study", "number": 0, "shape": "normal"}, {"card_name": "Merysk, Perpetual Storm", "number": 166, "shape": "normal"}, {"card_name": "Vrolos, Grand Resurrector", "number": 197, "shape": "normal"}, {"card_name": "A Mothers Wrath", "number": 167, "shape": "normal"}, {"card_name": "UG Utility Spell", "number": 195, "shape": "normal"}, {"card_name": "Inkling Summons", "number": 157, "shape": "normal"}, {"card_name": "Prophet of Thunder", "number": 173, "shape": "normal"}, {"card_name": "Asavah, Titan of the Swarm", "number": 202, "shape": "normal"}, {"card_name": "Lando, the Perfectionist", "number": 161, "shape": "normal"}, {"card_name": "e"}, {"card_name": "Judge of Life and Death", "number": 159, "shape": "normal"}, {"card_name": "Wang Chung", "number": 198, "shape": "normal"}, {"card_name": "The Hunt", "number": 156, "shape": "normal"}, {"card_name": "e"}, {"card_name": "e"}, {"card_name": "e"}, {"card_name": "Dragon Messengers", "number": 148, "shape": "normal"}, {"card_name": "Grisilda, Mayor of Sweettooth", "number": 153, "shape": "normal"}, {"card_name": "e"}, {"card_name": "e"}, {"card_name": "e"}, {"card_name": "Filigree Filibuster", "number": 149, "shape": "normal"}, {"card_name": "Pest Rain", "number": 171, "shape": "normal"}, {"card_name": "e"}, {"card_name": "e"}, {"card_name": "e"}, {"card_name": "Frenzied Search", "number": 150, "shape": "normal"}, {"card_name": "Surprise Kiss", "number": 192, "shape": "normal"}, {"card_name": "e"}, {"card_name": "e"}, {"card_name": "e"}, {"card_name": "Shaman of the Flames", "number": 182, "shape": "normal"}, {"card_name": "Golgari Terror Mites", "number": 203, "shape": "normal"}, {"card_name": "e"}, {"card_name": "e"}, {"card_name": "e"}, {"card_name": "Inventory Manager", "number": 158, "shape": "normal"}, {"card_name": "e"}, {"card_name": "e"}, {"card_name": "e"}, {"card_name": "e"}, {"card_name": "Rootha, Tenured Tutor", "number": 180, "shape": "normal"}, {"card_name": "e"}, {"card_name": "e"}, {"card_name": "e"}, {"card_name": "er"}, {"card_name": "er"}, {"card_name": "er"}, {"card_name": "er"}, {"card_name": "er"}, {"card_name": "Alela's Festival", "number": 201, "shape": "normal"}, {"card_name": "Viper's Bargain", "number": 196, "shape": "normal"}, {"card_name": "e"}, {"card_name": "Dancing in September", "number": 146, "shape": "normal"}, {"card_name": "Maple, the Non-Fungible", "number": 164, "shape": "normal"}, {"card_name": "Mist-Lure Shade", "number": 204, "shape": "normal"}, {"card_name": "e"}, {"card_name": "e"}, {"card_name": "Rebellious Inventor", "number": 176, "shape": "normal"}, {"card_name": "e"}, {"card_name": "er"}, {"card_name": "er"}, {"card_name": "er"}, {"card_name": "er"}, {"card_name": "er"}, {"card_name": "Hastur, King in Yellow", "number": 155, "shape": "normal"}, {"card_name": "Yog-Sothoth, Key and Gate", "number": 200, "shape": "normal"}, {"card_name": "The Creation of the Nyxborn", "number": 142, "shape": "saga"}, {"card_name": "Nyarlathotep, Crawling Chaos", "number": 169, "shape": "normal"}, {"card_name": "The Broken Vessel", "number": 140, "shape": "normal"}, {"card_name": "e"}, {"card_name": "The Custom Card Contest", "number": 145, "shape": "saga"}, {"card_name": "Shub-Niggurath, All Mother", "number": 184, "shape": "normal"}, {"card_name": "Ondy, Scavenging Trader", "number": 170, "shape": "normal"}, {"card_name": "Cthulu, the Great Dreamer", "number": 143, "shape": "normal"}, {"card_name": "e"}, {"card_name": "e"}, {"card_name": "Glorious Bounty", "number": 151, "shape": "normal"}, {"card_name": "Shay, Wastebin Wunderkind", "number": 183, "shape": "normal"}, {"card_name": "Broker of Bare Necessities", "number": 141, "shape": "normal"}, {"card_name": "e"}, {"card_name": "e"}, {"card_name": "Starfield Alignment", "number": 205, "shape": "normal"}, {"card_name": "e"}, {"card_name": "e"}, {"card_name": "er"}, {"card_name": "er"}, {"card_name": "er"}, {"card_name": "er"}, {"card_name": "er"}, {"card_name": "Ally Class", "number": 138, "shape": "class"}, {"card_name": "The Ur-Dragon's Call", "number": 239, "shape": "normal"}, {"card_name": "e"}, {"card_name": "e"}, {"card_name": "e"}, {"card_name": "er"}, {"card_name": "er"}, {"card_name": "er"}, {"card_name": "er"}, "a->colorless", {"card_name": "Cthulu, Awoken", "number": 1, "shape": "normal"}, {"card_name": "The DeLorean", "number": 207, "shape": "normal"}, {"card_name": "Endless Scrap Heap", "number": 209, "shape": "normal"}, {"card_name": "Ghost in the Machine", "number": 212, "shape": "normal"}, {"card_name": "Izekul, Waste Spreader", "number": 3, "shape": "normal"}, {"card_name": "The Angriest Reaver Drone", "number": 53, "shape": "class"}, {"card_name": "Force of Mobility", "number": 210, "shape": "normal"}, {"card_name": "Enslaved Estuary", "number": 2, "shape": "normal"}, {"card_name": "Space Derby", "number": 5, "shape": "normal"}, {"card_name": "Bounty Board", "number": 206, "shape": "normal"}, {"card_name": "Demonstration Aide", "number": 208, "shape": "normal"}, {"card_name": "Fort Cannon", "number": 211, "shape": "normal"}, {"card_name": "Golem Guard", "number": 213, "shape": "normal"}, {"card_name": "Murderous Dagger", "number": 215, "shape": "normal"}, {"card_name": "Snake Catepillar", "number": 4, "shape": "normal"}, {"card_name": "Morphing Urn", "number": 214, "shape": "normal"}, {"card_name": "e"}, {"card_name": "e"}, {"card_name": "e"}, {"card_name": "e"}, {"card_name": "er"}, {"card_name": "er"}, {"card_name": "er"}, {"card_name": "er"}, "a->land", {"card_name": "Seat of the Grand Cenobite", "number": 225, "shape": "normal"}, {"card_name": "e"}, {"card_name": "The Underworld", "number": 231, "shape": "normal"}, {"card_name": "Urabrask's Hidden Lair", "number": 115, "shape": "normal"}, {"card_name": "Titania's Court", "number": 230, "shape": "normal"}, {"card_name": "e"}, {"card_name": "e"}, {"card_name": "Yharnam", "number": 238, "shape": "normal"}, {"card_name": "Gremlin's Nest", "number": 221, "shape": "normal"}, {"card_name": "Ruins of Titania's Court", "number": 224, "shape": "normal"}, {"card_name": "er"}, {"card_name": "er"}, {"card_name": "er"}, {"card_name": "er"}, {"card_name": "er"}, {"card_name": "e"}, {"card_name": "e"}, {"card_name": "Gremlin Nest", "number": 220, "shape": "normal"}, {"card_name": "e"}, {"card_name": "e"}, {"card_name": "er"}, {"card_name": "er"}, {"card_name": "er"}, {"card_name": "er"}, {"card_name": "er"}, {"card_name": "Tenth District Square", "number": 227, "shape": "normal"}, {"card_name": "Urza's Workshop", "number": 236, "shape": "normal"}, {"card_name": "Restless Cascades", "number": 223, "shape": "normal"}, {"card_name": "Azerverl, Soul of Sands", "number": 216, "shape": "normal"}, {"card_name": "Doctor Black's Library", "number": 217, "shape": "normal"}, {"card_name": "Nezket, Dune Convergence", "number": 222, "shape": "normal"}, {"card_name": "Urza's Cloudpost", "number": 235, "shape": "normal"}, {"card_name": "e"}, {"card_name": "e"}, {"card_name": "e"}, {"card_name": "er"}, {"card_name": "er"}, {"card_name": "er"}, {"card_name": "er"}, {"card_name": "er"}]